{"nodes":[{"graphics":{},"id":"newnode-0","links":[{"graphics":{},"id":"newline-5","events":{},"class":null,"n1":"newnode-1","n2":"newnode-0","co":2.6,"t":0,"type":"link"},{"graphics":{},"id":"newline-6","events":{},"class":null,"n1":"newnode-2","n2":"newnode-0","co":-1.4,"t":0,"type":"link"}],"events":{},"notes":"empty notes","type":"node","class":null,"x":"1341","y":"343","name":"S","signal":0.518,"signal_fire":0},{"graphics":{},"id":"newnode-1","links":[{"graphics":{},"id":"newline-3","events":{},"class":null,"n1":"newnode-7","n2":"newnode-1","co":0.4,"t":0,"type":"link"},{"graphics":{},"id":"newline-4","events":{},"class":null,"n1":"newnode-4","n2":"newnode-1","co":0.5,"t":0,"type":"link"},{"graphics":{},"id":"newline-5","events":{},"class":null,"n1":"newnode-1","n2":"newnode-0","co":2.6,"t":0,"type":"link"},{"graphics":{},"id":"newline-9","events":{},"class":null,"n1":"newnode-8","n2":"newnode-1","co":0.75,"t":0,"type":"link"},{"graphics":{},"id":"newline-10","events":{},"class":null,"n1":"newnode-6","n2":"newnode-1","co":1.2,"t":24,"type":"link"},{"graphics":{},"id":"newline-11","events":{},"class":null,"n1":"newnode-1","n2":"newnode-3","co":1.8,"t":0,"type":"link"}],"events":{},"notes":"empty notes","type":"node","class":null,"x":"577","y":"345","name":"F","signal":0.07,"signal_fire":0},{"graphics":{},"id":"newnode-2","links":[{"graphics":{},"id":"newline-6","events":{},"class":null,"n1":"newnode-2","n2":"newnode-0","co":-1.4,"t":0,"type":"link"},{"graphics":{},"id":"newline-7","events":{},"class":null,"n1":"newnode-3","n2":"newnode-2","co":-1.6,"t":0,"type":"link"}],"events":{},"notes":"empty notes","type":"node","class":null,"x":"1151","y":"541","name":"H","signal":-0.24000000000000005,"signal_fire":0},{"graphics":{},"id":"newnode-3","links":[{"graphics":{},"id":"newline-7","events":{},"class":null,"n1":"newnode-3","n2":"newnode-2","co":-1.6,"t":0,"type":"link"},{"graphics":{},"id":"newline-8","events":{},"class":null,"n1":"newnode-4","n2":"newnode-3","co":0.4,"t":24,"type":"link"},{"graphics":{},"id":"newline-11","events":{},"class":null,"n1":"newnode-1","n2":"newnode-3","co":1.8,"t":0,"type":"link"}],"events":{},"notes":"empty notes","type":"node","class":null,"x":"878","y":"543","name":"G","signal":0.15000000000000002,"signal_fire":0},{"graphics":{},"id":"newnode-4","links":[{"graphics":{},"id":"newline-2","events":{},"class":null,"n1":"newnode-5","n2":"newnode-4","co":0.6,"t":12,"type":"link"},{"graphics":{},"id":"newline-4","events":{},"class":null,"n1":"newnode-4","n2":"newnode-1","co":0.5,"t":0,"type":"link"},{"graphics":{},"id":"newline-8","events":{},"class":null,"n1":"newnode-4","n2":"newnode-3","co":0.4,"t":24,"type":"link"}],"events":{},"notes":"empty notes","type":"node","class":null,"x":"575","y":"543","name":"E","signal":0.06,"signal_fire":0},{"graphics":{},"id":"newnode-5","links":[{"graphics":{},"id":"newline-2","events":{},"class":null,"n1":"newnode-5","n2":"newnode-4","co":0.6,"t":12,"type":"link"}],"events":{},"notes":"empty notes","type":"node","class":null,"x":"248","y":"544","name":"A","draw_type":"ORIGIN","signal":0,"signal_fire":0.1},{"graphics":{},"id":"newnode-6","links":[{"graphics":{},"id":"newline-10","events":{},"class":null,"n1":"newnode-6","n2":"newnode-1","co":1.2,"t":24,"type":"link"}],"events":{},"notes":"empty notes","type":"node","class":null,"x":"246","y":"113","name":"C","signal":0,"signal_fire":0},{"graphics":{},"id":"newnode-7","links":[{"graphics":{},"id":"newline-3","events":{},"class":null,"n1":"newnode-7","n2":"newnode-1","co":0.4,"t":0,"type":"link"}],"events":{},"notes":"empty notes","type":"node","class":null,"x":"246","y":"346","name":"B","draw_type":"ORIGIN","signal":0,"signal_fire":0.1},{"graphics":{},"id":"newnode-8","links":[{"graphics":{},"id":"newline-9","events":{},"class":null,"n1":"newnode-8","n2":"newnode-1","co":0.75,"t":0,"type":"link"}],"events":{},"notes":"empty notes","type":"node","class":null,"x":"576","y":"102","name":"D","signal":0,"signal_fire":0}],"links":[{"graphics":{},"id":"newline-2","events":{},"class":null,"n1":"newnode-5","n2":"newnode-4","co":0.6,"t":12,"type":"link"},{"graphics":{},"id":"newline-3","events":{},"class":null,"n1":"newnode-7","n2":"newnode-1","co":0.4,"t":0,"type":"link"},{"graphics":{},"id":"newline-4","events":{},"class":null,"n1":"newnode-4","n2":"newnode-1","co":0.5,"t":0,"type":"link"},{"graphics":{},"id":"newline-5","events":{},"class":null,"n1":"newnode-1","n2":"newnode-0","co":2.6,"t":0,"type":"link"},{"graphics":{},"id":"newline-6","events":{},"class":null,"n1":"newnode-2","n2":"newnode-0","co":-1.4,"t":0,"type":"link"},{"graphics":{},"id":"newline-7","events":{},"class":null,"n1":"newnode-3","n2":"newnode-2","co":-1.6,"t":0,"type":"link"},{"graphics":{},"id":"newline-8","events":{},"class":null,"n1":"newnode-4","n2":"newnode-3","co":0.4,"t":24,"type":"link"},{"graphics":{},"id":"newline-9","events":{},"class":null,"n1":"newnode-8","n2":"newnode-1","co":0.75,"t":0,"type":"link"},{"graphics":{},"id":"newline-10","events":{},"class":null,"n1":"newnode-6","n2":"newnode-1","co":1.2,"t":24,"type":"link"},{"graphics":{},"id":"newline-11","events":{},"class":null,"n1":"newnode-1","n2":"newnode-3","co":1.8,"t":0,"type":"link"}]}